legi/__init__.py
legi/anomalies.py
legi/articles.py
legi/db.py
legi/download.py
legi/export.py
legi/factorize.py
legi/fr_calendar.py
legi/french.py
legi/html.py
legi/normalize.py
legi/roman.py
legi/sections.py
legi/spelling.py
legi/stats.py
legi/tar2sqlite.py
legi/titles.py
legi/utils.py
legi/sql/migrations.sql
legi/sql/schema.sql
legi-0.5.dist-info/METADATA
legi-0.5.dist-info/WHEEL
legi-0.5.dist-info/top_level.txt
legi-0.5.dist-info/RECORD
