Metadata-Version: 2.1
Name: legi
Version: 0.5
Summary: Tools to work with the database of French laws (LEGI)
Home-page: https://github.com/Legilibre/legi.py
Author: Changaco
Author-email: changaco@changaco.oy.lc
License: CC0
Keywords: legi law france
Platform: UNKNOWN
Requires-Dist: appdirs
Requires-Dist: hunspell
Requires-Dist: libarchive-c
Requires-Dist: lxml
Requires-Dist: requests
Requires-Dist: tqdm
